MANIFEST.in
README.md
VERSION
requirements.txt
setup.cfg
setup.py
rhasspy_wake_raven.egg-info/PKG-INFO
rhasspy_wake_raven.egg-info/SOURCES.txt
rhasspy_wake_raven.egg-info/dependency_links.txt
rhasspy_wake_raven.egg-info/entry_points.txt
rhasspy_wake_raven.egg-info/requires.txt
rhasspy_wake_raven.egg-info/top_level.txt
rhasspywake_raven/__init__.py
rhasspywake_raven/__main__.py
rhasspywake_raven/dtw.py
rhasspywake_raven/py.typed
rhasspywake_raven/utils.py
tests/__init__.py
tests/test_dtw.py